.bumpversion.cfg
.editorconfig
.readthedocs.yml
AUTHORS.rst
CODE_OF_CONDUCT.md
MANIFEST.in
docs/Makefile
docs/authors.rst
docs/conf.py
docs/contributing.rst
docs/index.rst
docs/license.rst
docs/make.bat
docs/requirements.txt
opendebates/__init__.py
opendebates/utils.py
plugins/__init__.py
poetry.lock
tox.ini
opendebates-0.1.0a16.dist-info/LICENSE
opendebates-0.1.0a16.dist-info/WHEEL
opendebates-0.1.0a16.dist-info/METADATA
opendebates-0.1.0a16.dist-info/RECORD
